tests/__init__.py
tests/test_cleaner.py
tests/test_dectector.py
textminer/__init__.py
textminer/cleaner.py
textminer/detector.py
textminer/summarizer.py
textminer_prozzzzxcv-0.1.0.dist-info/METADATA
textminer_prozzzzxcv-0.1.0.dist-info/WHEEL
textminer_prozzzzxcv-0.1.0.dist-info/top_level.txt
textminer_prozzzzxcv-0.1.0.dist-info/RECORD
